s3_bucket/__init__.py
s3_bucket/s3_crud.py
s3_crud-0.2.dist-info/LICENSE
s3_crud-0.2.dist-info/METADATA
s3_crud-0.2.dist-info/WHEEL
s3_crud-0.2.dist-info/top_level.txt
s3_crud-0.2.dist-info/RECORD
